fortuna/__init__.py
fortuna/calib_model/__init__.py
fortuna/calib_model/base.py
fortuna/calib_model/calib_mixin.py
fortuna/calib_model/calib_model_calibrator.py
fortuna/calib_model/calib_state_repository.py
fortuna/calib_model/classification.py
fortuna/calib_model/config/__init__.py
fortuna/calib_model/config/base.py
fortuna/calib_model/config/callback.py
fortuna/calib_model/config/checkpointer.py
fortuna/calib_model/config/hyperparameters.py
fortuna/calib_model/config/monitor.py
fortuna/calib_model/config/optimizer.py
fortuna/calib_model/config/processor.py
fortuna/calib_model/loss.py
fortuna/calib_model/predictive/__init__.py
fortuna/calib_model/predictive/base.py
fortuna/calib_model/predictive/classification.py
fortuna/calib_model/predictive/regression.py
fortuna/calib_model/regression.py
fortuna/calib_model/state.py
fortuna/calibration/__init__.py
fortuna/calibration/binary_classification/__init__.py
fortuna/calibration/binary_classification/temp_scaling/__init__.py
fortuna/calibration/binary_classification/temp_scaling/base.py
fortuna/calibration/binary_classification/temp_scaling/bias_binary_temp_scaling.py
fortuna/calibration/binary_classification/temp_scaling/brier_binary_temp_scaling.py
fortuna/calibration/binary_classification/temp_scaling/crossentropy_binary_temp_scaling.py
fortuna/calibration/binary_classification/temp_scaling/f1_temp_scaling.py
fortuna/calibration/classification/__init__.py
fortuna/calibration/classification/temp_scaling/__init__.py
fortuna/calibration/classification/temp_scaling/base.py
fortuna/conformal/__init__.py
fortuna/conformal/classification/__init__.py
fortuna/conformal/classification/adaptive_conformal_classifier.py
fortuna/conformal/classification/adaptive_prediction.py
fortuna/conformal/classification/base.py
fortuna/conformal/classification/maxcovfixprec_binary_classfication.py
fortuna/conformal/classification/simple_prediction.py
fortuna/conformal/multivalid/__init__.py
fortuna/conformal/multivalid/base.py
aws_fortuna-0.2.0.dist-info/LICENSE
aws_fortuna-0.2.0.dist-info/METADATA
aws_fortuna-0.2.0.dist-info/NOTICE
aws_fortuna-0.2.0.dist-info/WHEEL
aws_fortuna-0.2.0.dist-info/RECORD
