Metadata-Version: 2.1
Name: aws-fortuna
Version: 0.2.0
Summary: A Library for Uncertainty Quantification.
License: Apache-2.0
Author: Gianluca Detommaso
Author-email: gianluca.detommaso@gmail.com
Requires-Python: >=3.9,<3.12
Classifier: License :: OSI Approved :: Apache Software License
Classifier: Programming Language :: Python :: 3
Classifier: Programming Language :: Python :: 3.9
Classifier: Programming Language :: Python :: 3.10
Classifier: Programming Language :: Python :: 3.11
Provides-Extra: docs
Provides-Extra: hallucination
Provides-Extra: notebooks
Provides-Extra: sagemaker
Provides-Extra: transformers
Requires-Dist: Sphinx (>=7.0.0,<8.0.0) ; extra == "docs"
Requires-Dist: array-record (==0.4.1) ; sys_platform == "darwin"
Requires-Dist: boto3 (>=1.26.145,<2.0.0) ; extra == "sagemaker"
Requires-Dist: datasets (>=2.11.0,<3.0.0) ; extra == "transformers" or extra == "hallucination"
Requires-Dist: flax (>=0.8.5,<0.9.0)
Requires-Dist: hydra-core (>=1.3.2,<2.0.0) ; extra == "sagemaker"
Requires-Dist: ipython (>=8.7.0,<9.0.0) ; extra == "docs"
Requires-Dist: jax (>=0.4.30,<0.5.0)
Requires-Dist: jupyter (>=1.0.0,<2.0.0) ; extra == "notebooks"
Requires-Dist: matplotlib (>=3.6.2,<4.0.0)
Requires-Dist: nbsphinx (>=0.8.10,<0.9.0) ; extra == "docs"
Requires-Dist: nbsphinx-link (>=1.3.0,<2.0.0) ; extra == "docs"
Requires-Dist: numpy (>=1.23.4,<2.0.0)
Requires-Dist: optax (>=0.1.3,<0.2.0)
Requires-Dist: pydata-sphinx-theme (>=0.12.0,<0.13.0) ; extra == "docs"
Requires-Dist: sagemaker (>=2.161.0,<3.0.0) ; extra == "sagemaker"
Requires-Dist: sagemaker-utils (>=0.3.6,<0.4.0) ; extra == "sagemaker"
Requires-Dist: scikit-learn (>=1.3.2,<2.0.0) ; extra == "hallucination"
Requires-Dist: sphinx-autodoc-typehints (>=1.19.5,<2.0.0) ; extra == "docs"
Requires-Dist: sphinx-gallery (>=0.11.1,<0.12.0) ; extra == "docs"
Requires-Dist: tabulate (>=0.9.0,<0.10.0) ; extra == "docs"
Requires-Dist: tensorflow-cpu (>=2.11.0,<3.0.0) ; sys_platform != "darwin"
Requires-Dist: tensorflow-macos (==2.13.1) ; sys_platform == "darwin"
Requires-Dist: torch (>=2.1.0,<3.0.0) ; extra == "hallucination"
Requires-Dist: tqdm (>=4.64.1,<5.0.0)
Requires-Dist: transformers (>=4.28.1,<5.0.0) ; extra == "transformers" or extra == "hallucination"
Requires-Dist: umap-learn (>=0.5.5,<0.6.0) ; extra == "hallucination"
Project-URL: Documentation, https://aws-fortuna.readthedocs.io/en/latest/
